rcsbsearch/__init__.py
rcsbsearch/resources/metadata_schema.json
rcsbsearch/schema.py
rcsbsearch/search.py
rcsbsearch/update_schema.py
zeigen/__init__.py
zeigen/__main__.py
zeigen/common.py
zeigen/config.py
zeigen/convert.py
zeigen/find.py
zeigen/py.typed
zeigen/query.py
zeigen/rcsb_cache.py
zeigen/templates/zeigen.toml
zeigen-0.3.0.dist-info/entry_points.txt
zeigen-0.3.0.dist-info/LICENSE.logo.txt
zeigen-0.3.0.dist-info/LICENSE
zeigen-0.3.0.dist-info/LICENSE.rcsbsearch
zeigen-0.3.0.dist-info/WHEEL
zeigen-0.3.0.dist-info/METADATA
zeigen-0.3.0.dist-info/RECORD
