Metadata-Version: 2.1
Name: zeigen
Version: 0.3.0
Summary: Find water networks in atomic-resolution crystal structures
Home-page: https://github.com/hydrationdynamics/zeigen
License: BSD-3-Clause
Keywords: science,chemistry,physical chemistry,biology,structural biology,hydrated water
Author: Joel Berendzen
Author-email: joel@generisbio.com
Requires-Python: >=3.9.1,<3.11
Classifier: Development Status :: 4 - Beta
Classifier: Environment :: Console
Classifier: Intended Audience :: Science/Research
Classifier: License :: OSI Approved :: BSD License
Classifier: Natural Language :: English
Classifier: Operating System :: OS Independent
Classifier: Programming Language :: Python :: 3
Classifier: Programming Language :: Python :: 3.10
Classifier: Programming Language :: Python :: 3.10
Classifier: Programming Language :: Python :: 3.9
Classifier: Topic :: Scientific/Engineering :: Chemistry
Requires-Dist: attrs (>=21.4.0)
Requires-Dist: biopython (>=1.79)
Requires-Dist: colorama (>=0.4.4)
Requires-Dist: dotli (>=1.1)
Requires-Dist: dynaconf (>=3.1.7)
Requires-Dist: gemmi (>=0.5.2)
Requires-Dist: gql[all] (>=3.0.0)
Requires-Dist: jsonschema (>=4.16.0,<5.0.0)
Requires-Dist: loguru (>=0.6.0)
Requires-Dist: matplotlib (>=3.5.1)
Requires-Dist: numpy (>=1.22.1)
Requires-Dist: pandas (>=1.4.0)
Requires-Dist: pint (>=0.18)
Requires-Dist: progressbar2 (>=4.0.0,<5.0.0)
Requires-Dist: pyarrow (>=9.0.0)
Requires-Dist: requests (>=2.28.1,<3.0.0)
Requires-Dist: requests-download (>=0.1.2,<0.2.0)
Requires-Dist: schema (>=0.7.5)
Requires-Dist: scipy (>=1.7.3)
Requires-Dist: statsdict (>=0.1.5)
Requires-Dist: tabulate (>=0.8.9)
Requires-Dist: toml (>=0.10.2)
Requires-Dist: tqdm (>=4.64.1)
Requires-Dist: typer (>=0.4.0)
Requires-Dist: uncertainties (>=3.1.6)
Project-URL: Changelog, https://github.com/hydrationdynamics/zeigen/releases
Project-URL: Documentation, https://zeigen.readthedocs.io
Project-URL: Repository, https://github.com/hydrationdynamics/zeigen
